fdutils/__init__.py
fdutils/blp_utils.py
fdutils/wind_utils.py
fdutils-0.0.8.dist-info/LICENSE
fdutils-0.0.8.dist-info/METADATA
fdutils-0.0.8.dist-info/WHEEL
fdutils-0.0.8.dist-info/top_level.txt
fdutils-0.0.8.dist-info/RECORD
