Metadata-Version: 2.1
Name: fdutils
Version: 0.0.8
Summary: financial data sdk
Home-page: https://pypi.org/project/fdutils/
Author: teleping
Author-email: teleping@163.com
License: UNKNOWN
Project-URL: Bug Tracker, https://pypi.org/project/fdutils/
Platform: UNKNOWN
Classifier: Programming Language :: Python :: 3
Classifier: License :: OSI Approved :: MIT License
Classifier: Operating System :: OS Independent
Requires-Python: >=3.6
License-File: LICENSE
Requires-Dist: pandas
